jetmlgpt/__init__.py
jetmlgpt/static/index.js
jetmlgpt-0.1.3.data/data/etc/jupyter/jupyter_notebook_config.d/jetmlgpt.json
jetmlgpt-0.1.3.data/data/etc/jupyter/nbconfig/notebook.d/jetmlgpt.json
jetmlgpt-0.1.3.data/data/share/jupyter/nbextensions/jetmlgpt/index.js
jetmlgpt-0.1.3.dist-info/METADATA
jetmlgpt-0.1.3.dist-info/WHEEL
jetmlgpt-0.1.3.dist-info/top_level.txt
jetmlgpt-0.1.3.dist-info/RECORD
